{
  "id": 4,
  "topic": "숫자가 먼저 말한다",
  "thesis": "멜라누아는 형용사가 아니라 숫자를 먼저 내민다. 세 개의 검증값(0.00·97%·All N.D.)이 검정을 설명하는 방식이며, 각 숫자에 근거(시험)를 병기한다.",
  "images": [
    "black_powder(fine).png",
    "ink_on_skin_2.png",
    "ink_spread_on_glass.png",
    "PL-data-a.png",
    "PL-data-b.png"
  ],
  "slides": [
    {
      "type": "cover_stmt",
      "image": "molecular_structure.png",
      "lines": [
        "‘순하다’를 숫자로",
        "나타낼 수 있을까요?"
      ]
    },
    {
      "type": "body",
      "image": "ink_on_skin_2.png",
      "mode": "C",
      "num": "01",
      "title": "형용사로는 진실을 알 수 없습니다.",
      "segments": [
        [
          "‘순한’, ‘클린한’, ‘자연스러운’. 색소를 설명하는 형용사는 많지만, 그 기준은 말하는 사람마다 다릅니다. 피부에 수년간 남는 색이라면,",
          false
        ],
        [
          "느낌이 아니라 검증된 숫자로 봐야 합니다.",
          true
        ]
      ]
    },
    {
      "type": "body",
      "image": "ink_spread_on_glass.png",
      "mode": "A",
      "num": "02",
      "title": "그래서, 세 가지를 측정했습니다.",
      "segments": [
        [
          "멜라누아는 검정을 의료용 소재에 준하는 기준으로 시험했습니다. 피부 자극은 얼마나 되는지, 세포는 얼마나 살아남는지, 유해물질은 검출되는지.",
          false
        ],
        [
          "우리의 철학을, 숫자로 증명합니다.",
          true
        ]
      ]
    },
    {
      "type": "cover_data",
      "image": "PL-data-a.png",
      "number": "0.00",
      "label": "피부 자극 지수",
      "hook": "ISO 10993-23 · 측정 범위 최솟값"
    },
    {
      "type": "cover_data",
      "image": "PL-data-b.png",
      "number": "97%",
      "label": "세포 생존율",
      "hook": "세포독성 시험 · 비독성 기준 70%"
    },
    {
      "type": "cover_data",
      "image": "PL-data-a.png",
      "zoom": 1.3,
      "fx": 0.65,
      "fy": 0.4,
      "flip": true,
      "number": "All N.D.",
      "label": "유해물질 불검출 (필수 전항목)",
      "hook": "유해물질 자가품질검사 · 불검출"
    },
    {
      "type": "body",
      "image": "ink_on_skin_2.png",
      "zoom": 1.4,
      "fx": 0.6,
      "fy": 0.45,
      "flip": true,
      "mode": "A",
      "num": "03",
      "title": "숫자는, 비교할 수 있습니다.",
      "segments": [
        [
          "형용사는 비교하기 어렵지만, 숫자는 같은 기준 위에서 비교됩니다. 0.00, 97%, All N.D.는 시술자가 선택 전에 확인할 수 있는 정보입니다.",
          false
        ],
        [
          "알고 고르는 것과 모르고 쓰는 것은 다릅니다.",
          true
        ]
      ]
    },
    {
      "type": "closing",
      "lines": [
        "멜라누아는",
        "숫자를",
        "먼저 보여줍니다."
      ]
    }
  ],
  "caption": "‘순하다’, ‘클린하다’. 순수함을 설명하는 형용사는 많습니다. 하지만 피부에 수년간 남는 색이라면, 느낌이 아니라 검증된 숫자로 확인하는 편이 정직합니다.\n\n좋은 철학일수록 숫자로 증명되어야 한다고 믿습니다. 그래서 멜라누아는 검정을 의료용 소재에 준하는 기준으로 시험하고, 세 개의 숫자로 정리했습니다.\n· 피부 자극 지수 0.00 (ISO 10993-23, 측정 범위 최솟값)\n· 세포 생존율 97% (세포독성 시험, 비독성 기준 70%)\n· 유해물질 (필수 전항목) All N.D. (유해물질 자가품질검사, 불검출)\n\n시험 기준과 데이터는 멜라누아 홈페이지에서 확인하실 수 있습니다.\n\n더 알아보기 →\nmelanoir.co.kr/products/embo\n\n#멜라누아 #MELANOIR #반영구색소 #PMU #반영구화장 #반영구잉크 #멜라닌색소 #ISO10993 #세포독성 #PMUartist"
}